teaser/__init__.py
teaser/project.py
teaser/data/__init__.py
teaser/data/dataclass.py
teaser/data/utilities.py
teaser/data/input/__init__.py
teaser/data/input/buildingelement_input_json.py
teaser/data/input/material_input_json.py
teaser/data/input/teaserjson_input.py
teaser/data/input/usecond_input.py
teaser/data/input/inputdata/MaterialTemplates.json
teaser/data/input/inputdata/TypeElements_IWU.json
teaser/data/input/inputdata/TypeElements_KFW.json
teaser/data/input/inputdata/TypeElements_TABULA_DE.json
teaser/data/input/inputdata/TypeElements_TABULA_DK.json
teaser/data/input/inputdata/UseConditions.json
teaser/data/input/inputdata/__init__.py
teaser/data/input/inputdata/weatherdata/ASHRAE140.mos
teaser/data/input/inputdata/weatherdata/DEU_BW_Mannheim_107290_TRY2010_12_Jahr_BBSR.mos
teaser/data/input/inputdata/weatherdata/__init__.py
teaser/data/output/__init__.py
teaser/data/output/aixlib_output.py
teaser/data/output/besmod_output.py
teaser/data/output/buildingelement_output.py
teaser/data/output/ibpsa_output.py
teaser/data/output/material_output.py
teaser/data/output/modelica_output.py
teaser/data/output/runUnitTests.py
teaser/data/output/teaserjson_output.py
teaser/data/output/usecond_output.py
teaser/data/output/modelicatemplate/conversion
teaser/data/output/modelicatemplate/modelica_language
teaser/data/output/modelicatemplate/modelica_test_script
teaser/data/output/modelicatemplate/package
teaser/data/output/modelicatemplate/package_order
teaser/data/output/modelicatemplate/AixLib/AixLib_Multizone
teaser/data/output/modelicatemplate/AixLib/AixLib_ThermalZoneRecord_FiveElement
teaser/data/output/modelicatemplate/AixLib/AixLib_ThermalZoneRecord_FourElement
teaser/data/output/modelicatemplate/AixLib/AixLib_ThermalZoneRecord_OneElement
teaser/data/output/modelicatemplate/AixLib/AixLib_ThermalZoneRecord_ThreeElement
teaser/data/output/modelicatemplate/AixLib/AixLib_ThermalZoneRecord_TwoElement
teaser/data/output/modelicatemplate/BESMod/Building
teaser-1.3.0.dist-info/METADATA
teaser-1.3.0.dist-info/WHEEL
teaser-1.3.0.dist-info/top_level.txt
teaser-1.3.0.dist-info/RECORD
