Metadata-Version: 2.4
Name: teaser
Version: 1.3.0
Summary: Tool for Energy Analysis and Simulation for Efficient Retrofit 
Home-page: https://github.com/RWTH-EBC/TEASER
Download-URL: https://github.com/RWTH-EBC/TEASER/archive/refs/tags/1.3.0.tar.gz
Author: RWTH Aachen University, E.ON Energy Research Center, Institute of Energy Efficient Buildings and Indoor Climate
Author-email: ebc-teaser@eonerc.rwth-aachen.de
License: MIT
Classifier: License :: OSI Approved :: MIT License
Classifier: Operating System :: Microsoft :: Windows
Classifier: Operating System :: POSIX :: Linux
Classifier: Programming Language :: Python :: 3.7
Classifier: Programming Language :: Python :: 3.8
Classifier: Programming Language :: Python :: 3.9
Classifier: Programming Language :: Python :: 3.10
Classifier: Programming Language :: Python :: 3.11
Classifier: Intended Audience :: Science/Research
Classifier: Topic :: Software Development :: Code Generators
Classifier: Topic :: Scientific/Engineering
Classifier: Topic :: Utilities
Requires-Dist: mako
Requires-Dist: pytest
Requires-Dist: pandas
Requires-Dist: numpy
Provides-Extra: report
Requires-Dist: plotly; extra == "report"
Provides-Extra: simulation
Requires-Dist: ebcpy>=0.5.6; extra == "simulation"
Requires-Dist: fastparquet>=2023.1.0; extra == "simulation"
Dynamic: author
Dynamic: author-email
Dynamic: classifier
Dynamic: description
Dynamic: description-content-type
Dynamic: download-url
Dynamic: home-page
Dynamic: license
Dynamic: provides-extra
Dynamic: requires-dist
Dynamic: summary
